best/__init__.py
best/integration/__init__.py
best/unit/__init__.py
best/unit/conftest.py
best/unit/test_glue_session.py
best/unit/test_glue_session_demo.py
best/unit/test_session_apis.py
aws_cryptographic_material_providers-10.0.0.dist-info/LICENSE.txt
aws_cryptographic_material_providers-10.0.0.dist-info/METADATA
aws_cryptographic_material_providers-10.0.0.dist-info/WHEEL
aws_cryptographic_material_providers-10.0.0.dist-info/top_level.txt
aws_cryptographic_material_providers-10.0.0.dist-info/RECORD
