Metadata-Version: 2.1
Name: aws-cryptographic-material-providers
Version: 10.0.0
Summary: aws-cryptographic-material-providers
Author: aws crypto
Author-email: aws-cryptography@aws.com
Classifier: Programming Language :: Python :: 3
Classifier: License :: OSI Approved :: MIT License
Classifier: Operating System :: OS Independent
License-File: LICENSE.txt
